ukf_sqrt/__init__.py
ukf_sqrt/ukf_sqrt.py
ukf_sqrt/utils.py
pyUKFsqrt-0.0.1.dist-info/LICENSE
pyUKFsqrt-0.0.1.dist-info/METADATA
pyUKFsqrt-0.0.1.dist-info/WHEEL
pyUKFsqrt-0.0.1.dist-info/top_level.txt
pyUKFsqrt-0.0.1.dist-info/RECORD
