Metadata-Version: 2.1
Name: pyUKFsqrt
Version: 0.0.1
Summary: Square root implementation of UKF
Home-page: UNKNOWN
Author: Floris van Breugel
Author-email: fvanbreugel@unr.edu
License: UNKNOWN
Platform: UNKNOWN
Classifier: Programming Language :: Python :: 3
Classifier: License :: OSI Approved :: MIT License
Classifier: Operating System :: OS Independent
Requires-Python: >=2.7
